scrapy_pubsub/__init__.py
scrapy_pubsub/pipeline.py
scrapy_pubsub-0.0.3.dist-info/LICENSE
scrapy_pubsub-0.0.3.dist-info/METADATA
scrapy_pubsub-0.0.3.dist-info/WHEEL
scrapy_pubsub-0.0.3.dist-info/top_level.txt
scrapy_pubsub-0.0.3.dist-info/RECORD
